plexmix/__init__.py
plexmix/ai/__init__.py
plexmix/ai/base.py
plexmix/ai/claude_provider.py
plexmix/ai/cohere_provider.py
plexmix/ai/gemini_provider.py
plexmix/ai/local_provider.py
plexmix/ai/openai_provider.py
plexmix/ai/tag_generator.py
plexmix/cli/__init__.py
plexmix/cli/main.py
plexmix/config/__init__.py
plexmix/config/credentials.py
plexmix/config/settings.py
plexmix/database/__init__.py
plexmix/database/models.py
plexmix/database/recovery.py
plexmix/database/sqlite_manager.py
plexmix/database/vector_index.py
plexmix/playlist/__init__.py
plexmix/playlist/generator.py
plexmix/plex/__init__.py
plexmix/plex/client.py
plexmix/plex/sync.py
plexmix/ui/__init__.py
plexmix/ui/app.py
plexmix/ui/components/__init__.py
plexmix/ui/components/error.py
plexmix/ui/components/loading.py
plexmix/ui/components/navbar.py
plexmix/ui/components/progress_modal.py
plexmix/ui/components/toast.py
plexmix/ui/components/track_table.py
plexmix/ui/pages/__init__.py
plexmix/ui/pages/dashboard.py
plexmix/ui/pages/doctor.py
plexmix/ui/pages/generator.py
plexmix/ui/pages/history.py
plexmix/ui/pages/index.py
plexmix/ui/pages/library.py
plexmix/ui/pages/settings.py
plexmix/ui/pages/tagging.py
plexmix/ui/states/__init__.py
plexmix/ui/states/app_state.py
plexmix/ui/states/dashboard_state.py
plexmix/ui/states/doctor_state.py
plexmix/ui/states/generator_state.py
plexmix/ui/states/history_state.py
plexmix/ui/states/library_state.py
plexmix/ui/states/settings_state.py
plexmix/ui/states/tagging_state.py
plexmix/ui/utils/__init__.py
plexmix/ui/utils/validation.py
plexmix/utils/__init__.py
plexmix/utils/embeddings.py
plexmix/utils/logging.py
plexmix-0.4.0.dist-info/METADATA
plexmix-0.4.0.dist-info/WHEEL
plexmix-0.4.0.dist-info/entry_points.txt
plexmix-0.4.0.dist-info/RECORD
