Metadata-Version: 2.4
Name: plexmix
Version: 0.4.0
Summary: AI-powered Plex playlist generator using mood-based queries
License: MIT
Author: Anthony Izzo
Requires-Python: >=3.10,<4.0
Classifier: License :: OSI Approved :: MIT License
Classifier: Programming Language :: Python :: 3
Classifier: Programming Language :: Python :: 3.10
Classifier: Programming Language :: Python :: 3.11
Classifier: Programming Language :: Python :: 3.12
Classifier: Programming Language :: Python :: 3.13
Classifier: Programming Language :: Python :: 3.14
Provides-Extra: ui
Requires-Dist: anthropic (>=0.8.0,<0.9.0)
Requires-Dist: click (>=8.2,<9.0)
Requires-Dist: faiss-cpu (>=1.7.4,<2.0.0)
Requires-Dist: google-generativeai (>=0.3.0,<0.4.0)
Requires-Dist: keyring (>=24.3.0,<25.0.0)
Requires-Dist: numpy (>=1.26.0,<2.0.0)
Requires-Dist: openai (>=1.6.0,<2.0.0)
Requires-Dist: plexapi (>=4.15.0,<5.0.0)
Requires-Dist: pydantic (>=2.5.0,<3.0.0)
Requires-Dist: pydantic-settings (>=2.1.0,<3.0.0)
Requires-Dist: python-dotenv (>=1.0.0,<2.0.0)
Requires-Dist: pyyaml (>=6.0.1,<7.0.0)
Requires-Dist: reflex (>=0.8.23,<0.9.0) ; extra == "ui"
Requires-Dist: rich (>=13.7.0,<14.0.0)
Requires-Dist: sentence-transformers (>=2.2.0,<3.0.0)
Requires-Dist: typer (>=0.21.0,<0.22.0)
